rubiBot/__init__.py
rubiBot/config.py
rubiBot/getadress.py
rubiBot/methods.py
rubiBot/postdata.py
rubiBot-1.0.1.dist-info/LICENCE
rubiBot-1.0.1.dist-info/METADATA
rubiBot-1.0.1.dist-info/WHEEL
rubiBot-1.0.1.dist-info/top_level.txt
rubiBot-1.0.1.dist-info/RECORD
