Metadata-Version: 2.1
Name: rubiBot
Version: 1.0.1
Summary: rubiBot is a simple and fast Rubika Messenger library built for you
Home-page: https://rubika.ir/rubiBot_library
Author: Mohamad_Dark
Author-email: mr.mohamad.dark@gmail.com
License: MIT
Keywords: rubiBot_library,messenger,python2,python,python3,api,self,rubibot,Rubika,rubiBot,swiftrubika,rubi Bot,rubika,bot,robot,library,rubikalib,rubikalibrary,rubika.ir,RubiBot,m.rubika.ir
Classifier: Programming Language :: Python :: 3.6
Classifier: Programming Language :: Python :: 3.7
Classifier: Programming Language :: Python :: 3.8
Classifier: Programming Language :: Python :: 3.9
Classifier: Programming Language :: Python :: 3.10
Classifier: Programming Language :: Python :: 3.11
Classifier: License :: OSI Approved :: MIT License
Requires-Python: ~=3.7
License-File: LICENCE
Requires-Dist: requests
Requires-Dist: urllib3
Requires-Dist: pycryptodome
Requires-Dist: colorama
Requires-Dist: tinytag
Requires-Dist: aiohttp
